multimedeval/__init__.py
multimedeval/chestxray14.py
multimedeval/chexbert/__init__.py
multimedeval/chexbert/bert_tokenizer.py
multimedeval/chexbert/constants.py
multimedeval/chexbert/datasets/__init__.py
multimedeval/chexbert/datasets/unlabeled_dataset.py
multimedeval/chexbert/label.py
multimedeval/chexbert/models/__init__.py
multimedeval/chexbert/models/bert_encoder.py
multimedeval/chexbert/utils.py
multimedeval/ct_rate.py
multimedeval/dynamic_datasets.py
multimedeval/engine.py
multimedeval/image_classification.py
multimedeval/mednli.py
multimedeval/mimic.py
multimedeval/mimic_iii.py
multimedeval/mnist.py
multimedeval/overrides_/__init__.py
multimedeval/overrides_/enforce.py
multimedeval/overrides_/final.py
multimedeval/overrides_/overrides.py
multimedeval/qa.py
multimedeval/radcliq-v1.dill
multimedeval/radgraph/__init__.py
multimedeval/radgraph/allennlp/__init__.py
multimedeval/radgraph/allennlp/__main__.py
multimedeval/radgraph/allennlp/commands/__init__.py
multimedeval/radgraph/allennlp/commands/evaluate.py
multimedeval/radgraph/allennlp/commands/find_learning_rate.py
multimedeval/radgraph/allennlp/commands/predict.py
multimedeval/radgraph/allennlp/commands/print_results.py
multimedeval/radgraph/allennlp/commands/subcommand.py
multimedeval/radgraph/allennlp/commands/test_install.py
multimedeval/radgraph/allennlp/commands/train.py
multimedeval/radgraph/allennlp/common/__init__.py
multimedeval/radgraph/allennlp/common/cached_transformers.py
multimedeval/radgraph/allennlp/common/checks.py
multimedeval/radgraph/allennlp/common/file_utils.py
multimedeval/radgraph/allennlp/common/from_params.py
multimedeval/radgraph/allennlp/common/lazy.py
multimedeval/radgraph/allennlp/common/logging.py
multimedeval/radgraph/allennlp/common/params.py
multimedeval/radgraph/allennlp/common/plugins.py
multimedeval/radgraph/allennlp/common/registrable.py
multimedeval/radgraph/allennlp/common/testing/__init__.py
multimedeval/radgraph/allennlp/common/testing/distributed_test.py
multimedeval-1.0.0.dist-info/LICENSE
multimedeval-1.0.0.dist-info/METADATA
multimedeval-1.0.0.dist-info/WHEEL
multimedeval-1.0.0.dist-info/RECORD
