Metadata-Version: 2.3
Name: multimedeval
Version: 1.0.0
Summary: A Python tool to evaluate the performance of VLM on the medical domain.
License: MIT
Keywords: evaluation,medical,vlm
Author: Corentin Royer
Requires-Python: >=3.9,<3.13
Classifier: License :: OSI Approved :: MIT License
Classifier: Operating System :: OS Independent
Classifier: Programming Language :: Python :: 3
Classifier: Programming Language :: Python :: 3.9
Classifier: Programming Language :: Python :: 3.10
Classifier: Programming Language :: Python :: 3.11
Classifier: Programming Language :: Python :: 3.12
Requires-Dist: Pillow (>=10.2.0)
Requires-Dist: bert_score
Requires-Dist: datasets (>=2.16)
Requires-Dist: dotmap (>=1.3.30,<2.0.0)
Requires-Dist: gdown
Requires-Dist: h5py
Requires-Dist: jsonpickle
Requires-Dist: kaggle
Requires-Dist: medmnist
Requires-Dist: nibabel
Requires-Dist: nltk
Requires-Dist: protobuf
Requires-Dist: pydicom
Requires-Dist: scikit-learn (==1.3.2)
Requires-Dist: spacy (>=3.6.0,<3.8.4)
Requires-Dist: statsmodels
Requires-Dist: torch
Requires-Dist: torchmetrics
Requires-Dist: transformers
Requires-Dist: types-requests
Project-URL: Documentation, https://github.com/corentin-ryr/MultiMedEval
Project-URL: Homepage, https://github.com/corentin-ryr/MultiMedEval
Project-URL: Repository, https://github.com/corentin-ryr/MultiMedEval
